zotac/__init__.py
zotac/config.json
zotac/config.py
zotac/lib.py
zotac/zotac.py
zotac-0.0.4.dist-info/LICENSE
zotac-0.0.4.dist-info/METADATA
zotac-0.0.4.dist-info/WHEEL
zotac-0.0.4.dist-info/entry_points.txt
zotac-0.0.4.dist-info/top_level.txt
zotac-0.0.4.dist-info/RECORD
