Metadata-Version: 2.1
Name: zotac
Version: 0.0.4
Summary: Zotac tools
Home-page: https://eforce1.feld.cvut.cz/gitlab/eforce-driveless/zotac
Author: Tomas Roun
Author-email: tomas.roun8@gmail.com
License: UNKNOWN
Platform: UNKNOWN
Classifier: Programming Language :: Python :: 3
Classifier: License :: OSI Approved :: MIT License
Classifier: Operating System :: POSIX :: Linux
Classifier: Operating System :: MacOS :: MacOS X
Requires-Python: >=3.6
License-File: LICENSE
Requires-Dist: click (==8.0.1)
